<?xml version="1.0"?>

<world>

  <robot name="robot_sphere" file="../../robots/sphere.urdf"/>

  <rigidObject name="cylinder" file="../../terrains/primitives/cylinder_height_2_00_radius_0_50.stl" translation="+0 +0 +1"/>
  <rigidObject name="plate" file="../../terrains/primitives/plane.tri"/>

  <plannerinput>

    <qinit  config="6  +0.1 +2 +0.8 0 0 0  0 0 0 0 0"/>
    <qgoal  config="6  +0.1 -2 +0.1 0 0 0  0 0 0 0 0"/>
    <se3min config="6  -2 -3 -2 -3.141593 -1.57 -3.141593"/>
    <se3max config="6  +2 +3 +2 +3.141593 +1.57 +3.141593"/>

    <epsilongoalregion>0.01</epsilongoalregion>
    <maxplanningtime>120</maxplanningtime>      <!-- runtime in (s) --> 
    <freeFloating>1</freeFloating>      <!-- runtime in (s) --> 
    <pathWidth>0.1</pathWidth>
    <!-- <threading>1</threading> -->

    <algorithm name="multilevel:minimaspanner"/>

    <multilevel>
      <level robot_index="0" type="R3"/>
    </multilevel>

  </plannerinput>

</world>

